{"time":{"updated":"Apr 21, 2024 15:39:25 UTC","updatedISO":"2024-04-21T15:39:25+00:00","updateduk":"Apr 21, 2024 at 16:39 BST"},"disclaimer":"This data was produced from the CoinDesk Bitcoin Price Index (USD). Non-USD currency data converted using hourly conversion rate from openexchangerates.org","chartName":"Bitcoin","bpi":{"USD":{"code":"USD","symbol":"&#36;","rate":"65,167.859","description":"United States Dollar","rate_float":65167.8585},"GBP":{"code":"GBP","symbol":"&pound;","rate":"52,686.454","description":"British Pound Sterling","rate_float":52686.4541},"EUR":{"code":"EUR","symbol":"&euro;","rate":"61,080.074","description":"Euro","rate_float":61080.0743},"CNY":{"code":"CNY","symbol":"&yen;","rate":"471,769.678","description":"Chinese Yuan","rate_float":471769.6782}}}