{"time":{"updated":"Aug 6, 2024 08:59:58 UTC","updatedISO":"2024-08-06T08:59:58+00:00","updateduk":"Aug 6, 2024 at 09:59 BST"},"disclaimer":"This data was produced from the CoinDesk Bitcoin Price Index (USD). Non-USD currency data converted using hourly conversion rate from openexchangerates.org","chartName":"Bitcoin","bpi":{"USD":{"code":"USD","symbol":"&#36;","rate":"55,161.881","description":"United States Dollar","rate_float":55161.8813},"GBP":{"code":"GBP","symbol":"&pound;","rate":"43,297.498","description":"British Pound Sterling","rate_float":43297.4984},"EUR":{"code":"EUR","symbol":"&euro;","rate":"50,482.554","description":"Euro","rate_float":50482.5541},"CNY":{"code":"CNY","symbol":"&yen;","rate":"393,684.831","description":"Chinese Yuan","rate_float":393684.8309}}}