{"time":{"updated":"Jun 9, 2024 03:44:25 UTC","updatedISO":"2024-06-09T03:44:25+00:00","updateduk":"Jun 9, 2024 at 04:44 BST"},"disclaimer":"This data was produced from the CoinDesk Bitcoin Price Index (USD). Non-USD currency data converted using hourly conversion rate from openexchangerates.org","chartName":"Bitcoin","bpi":{"USD":{"code":"USD","symbol":"&#36;","rate":"69,367.619","description":"United States Dollar","rate_float":69367.619},"GBP":{"code":"GBP","symbol":"&pound;","rate":"54,499.988","description":"British Pound Sterling","rate_float":54499.9879},"EUR":{"code":"EUR","symbol":"&euro;","rate":"64,185.858","description":"Euro","rate_float":64185.8579},"CNY":{"code":"CNY","symbol":"&yen;","rate":"502,637.768","description":"Chinese Yuan","rate_float":502637.7676}}}