{"time":{"updated":"Jan 26, 2024 04:29:03 UTC","updatedISO":"2024-01-26T04:29:03+00:00","updateduk":"Jan 26, 2024 at 04:29 GMT"},"disclaimer":"This data was produced from the CoinDesk Bitcoin Price Index (USD). Non-USD currency data converted using hourly conversion rate from openexchangerates.org","chartName":"Bitcoin","bpi":{"USD":{"code":"USD","symbol":"&#36;","rate":"40,167.485","description":"United States Dollar","rate_float":40167.4845},"GBP":{"code":"GBP","symbol":"&pound;","rate":"31,600.443","description":"British Pound Sterling","rate_float":31600.4429},"EUR":{"code":"EUR","symbol":"&euro;","rate":"37,037.875","description":"Euro","rate_float":37037.8751},"CNY":{"code":"CNY","symbol":"&yen;","rate":"285,150.981","description":"Chinese Yuan","rate_float":285150.9806}}}