{"time":{"updated":"Aug 3, 2024 21:10:29 UTC","updatedISO":"2024-08-03T21:10:29+00:00","updateduk":"Aug 3, 2024 at 22:10 BST"},"disclaimer":"This data was produced from the CoinDesk Bitcoin Price Index (USD). Non-USD currency data converted using hourly conversion rate from openexchangerates.org","chartName":"Bitcoin","bpi":{"USD":{"code":"USD","symbol":"&#36;","rate":"60,208.871","description":"United States Dollar","rate_float":60208.8711},"GBP":{"code":"GBP","symbol":"&pound;","rate":"47,016.144","description":"British Pound Sterling","rate_float":47016.1441},"EUR":{"code":"EUR","symbol":"&euro;","rate":"55,154.035","description":"Euro","rate_float":55154.0353},"CNY":{"code":"CNY","symbol":"&yen;","rate":"431,047.35","description":"Chinese Yuan","rate_float":431047.3499}}}