{"time":{"updated":"May 22, 2024 23:36:21 UTC","updatedISO":"2024-05-22T23:36:21+00:00","updateduk":"May 23, 2024 at 00:36 BST"},"disclaimer":"This data was produced from the CoinDesk Bitcoin Price Index (USD). Non-USD currency data converted using hourly conversion rate from openexchangerates.org","chartName":"Bitcoin","bpi":{"USD":{"code":"USD","symbol":"&#36;","rate":"69,025.199","description":"United States Dollar","rate_float":69025.1992},"GBP":{"code":"GBP","symbol":"&pound;","rate":"54,261.261","description":"British Pound Sterling","rate_float":54261.2613},"EUR":{"code":"EUR","symbol":"&euro;","rate":"63,762.235","description":"Euro","rate_float":63762.2349},"CNY":{"code":"CNY","symbol":"&yen;","rate":"490,741.556","description":"Chinese Yuan","rate_float":490741.5564}}}