{"time":{"updated":"Jan 11, 2024 19:32:32 UTC","updatedISO":"2024-01-11T19:32:32+00:00","updateduk":"Jan 11, 2024 at 19:32 GMT"},"disclaimer":"This data was produced from the CoinDesk Bitcoin Price Index (USD). Non-USD currency data converted using hourly conversion rate from openexchangerates.org","chartName":"Bitcoin","bpi":{"USD":{"code":"USD","symbol":"&#36;","rate":"46,508.155","description":"United States Dollar","rate_float":46508.1545},"GBP":{"code":"GBP","symbol":"&pound;","rate":"36,483.833","description":"British Pound Sterling","rate_float":36483.8334},"EUR":{"code":"EUR","symbol":"&euro;","rate":"42,415.483","description":"Euro","rate_float":42415.4834},"CNY":{"code":"CNY","symbol":"&yen;","rate":"330,500.899","description":"Chinese Yuan","rate_float":330500.8985}}}