{"time":{"updated":"Nov 29, 2024 09:28:43 UTC","updatedISO":"2024-11-29T09:28:43+00:00","updateduk":"Nov 29, 2024 at 09:28 GMT"},"disclaimer":"This data was produced from the CoinDesk Bitcoin Price Index (USD). Non-USD currency data converted using hourly conversion rate from openexchangerates.org","chartName":"Bitcoin","bpi":{"USD":{"code":"USD","symbol":"&#36;","rate":"96,163.213","description":"United States Dollar","rate_float":96163.2127},"GBP":{"code":"GBP","symbol":"&pound;","rate":"75,692.757","description":"British Pound Sterling","rate_float":75692.7573},"EUR":{"code":"EUR","symbol":"&euro;","rate":"90,975.784","description":"Euro","rate_float":90975.7844},"CNY":{"code":"CNY","symbol":"&yen;","rate":"695,673.53","description":"Chinese Yuan","rate_float":695673.5299}}}