{"time":{"updated":"Mar 21, 2024 09:25:31 UTC","updatedISO":"2024-03-21T09:25:31+00:00","updateduk":"Mar 21, 2024 at 09:25 GMT"},"disclaimer":"This data was produced from the CoinDesk Bitcoin Price Index (USD). Non-USD currency data converted using hourly conversion rate from openexchangerates.org","chartName":"Bitcoin","bpi":{"USD":{"code":"USD","symbol":"&#36;","rate":"67,364.063","description":"United States Dollar","rate_float":67364.0628},"GBP":{"code":"GBP","symbol":"&pound;","rate":"52,768.089","description":"British Pound Sterling","rate_float":52768.0892},"EUR":{"code":"EUR","symbol":"&euro;","rate":"61,846.272","description":"Euro","rate_float":61846.2724},"CNY":{"code":"CNY","symbol":"&yen;","rate":"484,967.361","description":"Chinese Yuan","rate_float":484967.3607}}}