{"time":{"updated":"Aug 1, 2024 06:59:02 UTC","updatedISO":"2024-08-01T06:59:02+00:00","updateduk":"Aug 1, 2024 at 07:59 BST"},"disclaimer":"This data was produced from the CoinDesk Bitcoin Price Index (USD). Non-USD currency data converted using hourly conversion rate from openexchangerates.org","chartName":"Bitcoin","bpi":{"USD":{"code":"USD","symbol":"&#36;","rate":"64,343.402","description":"United States Dollar","rate_float":64343.4019},"GBP":{"code":"GBP","symbol":"&pound;","rate":"50,080.271","description":"British Pound Sterling","rate_float":50080.2713},"EUR":{"code":"EUR","symbol":"&euro;","rate":"59,428.917","description":"Euro","rate_float":59428.9172},"CNY":{"code":"CNY","symbol":"&yen;","rate":"465,312.179","description":"Chinese Yuan","rate_float":465312.1792}}}