{"time":{"updated":"Aug 10, 2022 19:44:00 UTC","updatedISO":"2022-08-10T19:44:00+00:00","updateduk":"Aug 10, 2022 at 20:44 BST"},"disclaimer":"This data was produced from the CoinDesk Bitcoin Price Index (USD). Non-USD currency data converted using hourly conversion rate from openexchangerates.org","chartName":"Bitcoin","bpi":{"USD":{"code":"USD","symbol":"&#36;","rate":"23,630.3569","description":"United States Dollar","rate_float":23630.3569},"GBP":{"code":"GBP","symbol":"&pound;","rate":"19,745.3372","description":"British Pound Sterling","rate_float":19745.3372},"EUR":{"code":"EUR","symbol":"&euro;","rate":"23,019.4176","description":"Euro","rate_float":23019.4176},"CNY":{"code":"CNY","symbol":"&yen;","rate":"40,202.5000","description":"Chinese Yuan","rate_float":40202.5}}}