{"time":{"updated":"Jan 12, 2025 19:52:26 UTC","updatedISO":"2025-01-12T19:52:26+00:00","updateduk":"Jan 12, 2025 at 19:52 GMT"},"disclaimer":"This data was produced from the CoinDesk Bitcoin Price Index (USD). Non-USD currency data converted using hourly conversion rate from openexchangerates.org","chartName":"Bitcoin","bpi":{"USD":{"code":"USD","symbol":"&#36;","rate":"95,941.652","description":"United States Dollar","rate_float":95941.6523},"GBP":{"code":"GBP","symbol":"&pound;","rate":"76,520.663","description":"British Pound Sterling","rate_float":76520.6634},"EUR":{"code":"EUR","symbol":"&euro;","rate":"92,270.349","description":"Euro","rate_float":92270.3491},"CNY":{"code":"CNY","symbol":"&yen;","rate":"703,050.834","description":"Chinese Yuan","rate_float":703050.8341}}}