{"time":{"updated":"Mar 21, 2024 18:32:12 UTC","updatedISO":"2024-03-21T18:32:12+00:00","updateduk":"Mar 21, 2024 at 18:32 GMT"},"disclaimer":"This data was produced from the CoinDesk Bitcoin Price Index (USD). Non-USD currency data converted using hourly conversion rate from openexchangerates.org","chartName":"Bitcoin","bpi":{"USD":{"code":"USD","symbol":"&#36;","rate":"65,443.414","description":"United States Dollar","rate_float":65443.4139},"GBP":{"code":"GBP","symbol":"&pound;","rate":"51,711.03","description":"British Pound Sterling","rate_float":51711.0297},"EUR":{"code":"EUR","symbol":"&euro;","rate":"60,272.468","description":"Euro","rate_float":60272.468},"CNY":{"code":"CNY","symbol":"&yen;","rate":"471,166.403","description":"Chinese Yuan","rate_float":471166.4027}}}