{"time":{"updated":"Mar 14, 2024 20:57:59 UTC","updatedISO":"2024-03-14T20:57:59+00:00","updateduk":"Mar 14, 2024 at 20:57 GMT"},"disclaimer":"This data was produced from the CoinDesk Bitcoin Price Index (USD). Non-USD currency data converted using hourly conversion rate from openexchangerates.org","chartName":"Bitcoin","bpi":{"USD":{"code":"USD","symbol":"&#36;","rate":"70,820.597","description":"United States Dollar","rate_float":70820.5968},"GBP":{"code":"GBP","symbol":"&pound;","rate":"55,519.311","description":"British Pound Sterling","rate_float":55519.3111},"EUR":{"code":"EUR","symbol":"&euro;","rate":"65,026.126","description":"Euro","rate_float":65026.1264},"CNY":{"code":"CNY","symbol":"&yen;","rate":"509,462.127","description":"Chinese Yuan","rate_float":509462.1273}}}