{"time":{"updated":"Mar 25, 2024 22:57:26 UTC","updatedISO":"2024-03-25T22:57:26+00:00","updateduk":"Mar 25, 2024 at 22:57 GMT"},"disclaimer":"This data was produced from the CoinDesk Bitcoin Price Index (USD). Non-USD currency data converted using hourly conversion rate from openexchangerates.org","chartName":"Bitcoin","bpi":{"USD":{"code":"USD","symbol":"&#36;","rate":"70,325.163","description":"United States Dollar","rate_float":70325.1628},"GBP":{"code":"GBP","symbol":"&pound;","rate":"55,654.068","description":"British Pound Sterling","rate_float":55654.068},"EUR":{"code":"EUR","symbol":"&euro;","rate":"64,894.654","description":"Euro","rate_float":64894.6537},"CNY":{"code":"CNY","symbol":"&yen;","rate":"507,002.229","description":"Chinese Yuan","rate_float":507002.2285}}}