{"time":{"updated":"Sep 14, 2023 16:28:00 UTC","updatedISO":"2023-09-14T16:28:00+00:00","updateduk":"Sep 14, 2023 at 17:28 BST"},"disclaimer":"This data was produced from the CoinDesk Bitcoin Price Index (USD). Non-USD currency data converted using hourly conversion rate from openexchangerates.org","chartName":"Bitcoin","bpi":{"USD":{"code":"USD","symbol":"&#36;","rate":"26,631.3413","description":"United States Dollar","rate_float":26631.3413},"GBP":{"code":"GBP","symbol":"&pound;","rate":"22,252.9358","description":"British Pound Sterling","rate_float":22252.9358},"EUR":{"code":"EUR","symbol":"&euro;","rate":"25,942.8146","description":"Euro","rate_float":25942.8146},"CNY":{"code":"CNY","symbol":"&yen;","rate":"40,202.5000","description":"Chinese Yuan","rate_float":40202.5}}}