{"time":{"updated":"Jan 18, 2022 14:07:00 UTC","updatedISO":"2022-01-18T14:07:00+00:00","updateduk":"Jan 18, 2022 at 14:07 GMT"},"disclaimer":"This data was produced from the CoinDesk Bitcoin Price Index (USD). Non-USD currency data converted using hourly conversion rate from openexchangerates.org","chartName":"Bitcoin","bpi":{"USD":{"code":"USD","symbol":"&#36;","rate":"41,583.5569","description":"United States Dollar","rate_float":41583.5569},"GBP":{"code":"GBP","symbol":"&pound;","rate":"30,576.4725","description":"British Pound Sterling","rate_float":30576.4725},"EUR":{"code":"EUR","symbol":"&euro;","rate":"36,546.4575","description":"Euro","rate_float":36546.4575},"CNY":{"code":"CNY","symbol":"&yen;","rate":"40,202.5000","description":"Chinese Yuan","rate_float":40202.5}}}