{"time":{"updated":"Apr 12, 2024 09:50:42 UTC","updatedISO":"2024-04-12T09:50:42+00:00","updateduk":"Apr 12, 2024 at 10:50 BST"},"disclaimer":"This data was produced from the CoinDesk Bitcoin Price Index (USD). Non-USD currency data converted using hourly conversion rate from openexchangerates.org","chartName":"Bitcoin","bpi":{"USD":{"code":"USD","symbol":"&#36;","rate":"70,570.279","description":"United States Dollar","rate_float":70570.2786},"GBP":{"code":"GBP","symbol":"&pound;","rate":"56,419.597","description":"British Pound Sterling","rate_float":56419.5969},"EUR":{"code":"EUR","symbol":"&euro;","rate":"66,129.503","description":"Euro","rate_float":66129.5027},"CNY":{"code":"CNY","symbol":"&yen;","rate":"510,710.05","description":"Chinese Yuan","rate_float":510710.0495}}}