{"time":{"updated":"Mar 10, 2024 14:24:38 UTC","updatedISO":"2024-03-10T14:24:38+00:00","updateduk":"Mar 10, 2024 at 14:24 GMT"},"disclaimer":"This data was produced from the CoinDesk Bitcoin Price Index (USD). Non-USD currency data converted using hourly conversion rate from openexchangerates.org","chartName":"Bitcoin","bpi":{"USD":{"code":"USD","symbol":"&#36;","rate":"69,423.434","description":"United States Dollar","rate_float":69423.4341},"GBP":{"code":"GBP","symbol":"&pound;","rate":"53,992.41","description":"British Pound Sterling","rate_float":53992.4097},"EUR":{"code":"EUR","symbol":"&euro;","rate":"63,438.023","description":"Euro","rate_float":63438.0233},"CNY":{"code":"CNY","symbol":"&yen;","rate":"498,855.971","description":"Chinese Yuan","rate_float":498855.9707}}}