{"time":{"updated":"Apr 23, 2024 21:58:11 UTC","updatedISO":"2024-04-23T21:58:11+00:00","updateduk":"Apr 23, 2024 at 22:58 BST"},"disclaimer":"This data was produced from the CoinDesk Bitcoin Price Index (USD). Non-USD currency data converted using hourly conversion rate from openexchangerates.org","chartName":"Bitcoin","bpi":{"USD":{"code":"USD","symbol":"&#36;","rate":"66,386.227","description":"United States Dollar","rate_float":66386.2269},"GBP":{"code":"GBP","symbol":"&pound;","rate":"53,325.268","description":"British Pound Sterling","rate_float":53325.2678},"EUR":{"code":"EUR","symbol":"&euro;","rate":"62,033.083","description":"Euro","rate_float":62033.0828},"CNY":{"code":"CNY","symbol":"&yen;","rate":"480,993.64","description":"Chinese Yuan","rate_float":480993.6396}}}