{"time":{"updated":"Jan 1, 2025 15:10:14 UTC","updatedISO":"2025-01-01T15:10:14+00:00","updateduk":"Jan 1, 2025 at 15:10 GMT"},"disclaimer":"This data was produced from the CoinDesk Bitcoin Price Index (USD). Non-USD currency data converted using hourly conversion rate from openexchangerates.org","chartName":"Bitcoin","bpi":{"USD":{"code":"USD","symbol":"&#36;","rate":"94,492.878","description":"United States Dollar","rate_float":94492.8778},"GBP":{"code":"GBP","symbol":"&pound;","rate":"75,356.18","description":"British Pound Sterling","rate_float":75356.1802},"EUR":{"code":"EUR","symbol":"&euro;","rate":"90,653.727","description":"Euro","rate_float":90653.7267},"CNY":{"code":"CNY","symbol":"&yen;","rate":"689,665.718","description":"Chinese Yuan","rate_float":689665.7182}}}