{"time":{"updated":"Jul 30, 2024 03:57:59 UTC","updatedISO":"2024-07-30T03:57:59+00:00","updateduk":"Jul 30, 2024 at 04:57 BST"},"disclaimer":"This data was produced from the CoinDesk Bitcoin Price Index (USD). Non-USD currency data converted using hourly conversion rate from openexchangerates.org","chartName":"Bitcoin","bpi":{"USD":{"code":"USD","symbol":"&#36;","rate":"66,571.735","description":"United States Dollar","rate_float":66571.7346},"GBP":{"code":"GBP","symbol":"&pound;","rate":"51,801.73","description":"British Pound Sterling","rate_float":51801.7302},"EUR":{"code":"EUR","symbol":"&euro;","rate":"61,537.846","description":"Euro","rate_float":61537.8463},"CNY":{"code":"CNY","symbol":"&yen;","rate":"483,497.194","description":"Chinese Yuan","rate_float":483497.1943}}}