{"time":{"updated":"Jan 25, 2023 16:15:00 UTC","updatedISO":"2023-01-25T16:15:00+00:00","updateduk":"Jan 25, 2023 at 16:15 GMT"},"disclaimer":"This data was produced from the CoinDesk Bitcoin Price Index (USD). Non-USD currency data converted using hourly conversion rate from openexchangerates.org","chartName":"Bitcoin","bpi":{"USD":{"code":"USD","symbol":"&#36;","rate":"22,619.9711","description":"United States Dollar","rate_float":22619.9711},"GBP":{"code":"GBP","symbol":"&pound;","rate":"18,901.0669","description":"British Pound Sterling","rate_float":18901.0669},"EUR":{"code":"EUR","symbol":"&euro;","rate":"22,035.1543","description":"Euro","rate_float":22035.1543},"CNY":{"code":"CNY","symbol":"&yen;","rate":"40,202.5000","description":"Chinese Yuan","rate_float":40202.5}}}