{"time":{"updated":"May 20, 2024 06:38:25 UTC","updatedISO":"2024-05-20T06:38:25+00:00","updateduk":"May 20, 2024 at 07:38 BST"},"disclaimer":"This data was produced from the CoinDesk Bitcoin Price Index (USD). Non-USD currency data converted using hourly conversion rate from openexchangerates.org","chartName":"Bitcoin","bpi":{"USD":{"code":"USD","symbol":"&#36;","rate":"66,998.905","description":"United States Dollar","rate_float":66998.905},"GBP":{"code":"GBP","symbol":"&pound;","rate":"52,728.473","description":"British Pound Sterling","rate_float":52728.4732},"EUR":{"code":"EUR","symbol":"&euro;","rate":"61,576.617","description":"Euro","rate_float":61576.6166},"CNY":{"code":"CNY","symbol":"&yen;","rate":"475,055.736","description":"Chinese Yuan","rate_float":475055.7357}}}