{"time":{"updated":"Dec 9, 2024 07:45:40 UTC","updatedISO":"2024-12-09T07:45:40+00:00","updateduk":"Dec 9, 2024 at 07:45 GMT"},"disclaimer":"This data was produced from the CoinDesk Bitcoin Price Index (USD). Non-USD currency data converted using hourly conversion rate from openexchangerates.org","chartName":"Bitcoin","bpi":{"USD":{"code":"USD","symbol":"&#36;","rate":"99,373.844","description":"United States Dollar","rate_float":99373.8444},"GBP":{"code":"GBP","symbol":"&pound;","rate":"78,054.975","description":"British Pound Sterling","rate_float":78054.9748},"EUR":{"code":"EUR","symbol":"&euro;","rate":"94,243.372","description":"Euro","rate_float":94243.3715},"CNY":{"code":"CNY","symbol":"&yen;","rate":"723,242.839","description":"Chinese Yuan","rate_float":723242.8393}}}