{"time":{"updated":"Apr 30, 2024 02:48:42 UTC","updatedISO":"2024-04-30T02:48:42+00:00","updateduk":"Apr 30, 2024 at 03:48 BST"},"disclaimer":"This data was produced from the CoinDesk Bitcoin Price Index (USD). Non-USD currency data converted using hourly conversion rate from openexchangerates.org","chartName":"Bitcoin","bpi":{"USD":{"code":"USD","symbol":"&#36;","rate":"63,862.351","description":"United States Dollar","rate_float":63862.351},"GBP":{"code":"GBP","symbol":"&pound;","rate":"50,888.331","description":"British Pound Sterling","rate_float":50888.3312},"EUR":{"code":"EUR","symbol":"&euro;","rate":"59,645.137","description":"Euro","rate_float":59645.1368},"CNY":{"code":"CNY","symbol":"&yen;","rate":"462,388.966","description":"Chinese Yuan","rate_float":462388.9661}}}