{"time":{"updated":"Aug 7, 2024 11:36:23 UTC","updatedISO":"2024-08-07T11:36:23+00:00","updateduk":"Aug 7, 2024 at 12:36 BST"},"disclaimer":"This data was produced from the CoinDesk Bitcoin Price Index (USD). Non-USD currency data converted using hourly conversion rate from openexchangerates.org","chartName":"Bitcoin","bpi":{"USD":{"code":"USD","symbol":"&#36;","rate":"57,206.301","description":"United States Dollar","rate_float":57206.3008},"GBP":{"code":"GBP","symbol":"&pound;","rate":"44,986.692","description":"British Pound Sterling","rate_float":44986.6917},"EUR":{"code":"EUR","symbol":"&euro;","rate":"52,394.908","description":"Euro","rate_float":52394.9076},"CNY":{"code":"CNY","symbol":"&yen;","rate":"410,815.608","description":"Chinese Yuan","rate_float":410815.6077}}}