{"time":{"updated":"Mar 5, 2024 19:53:26 UTC","updatedISO":"2024-03-05T19:53:26+00:00","updateduk":"Mar 5, 2024 at 19:53 GMT"},"disclaimer":"This data was produced from the CoinDesk Bitcoin Price Index (USD). Non-USD currency data converted using hourly conversion rate from openexchangerates.org","chartName":"Bitcoin","bpi":{"USD":{"code":"USD","symbol":"&#36;","rate":"61,211.266","description":"United States Dollar","rate_float":61211.2656},"GBP":{"code":"GBP","symbol":"&pound;","rate":"48,178.897","description":"British Pound Sterling","rate_float":48178.8974},"EUR":{"code":"EUR","symbol":"&euro;","rate":"56,401.04","description":"Euro","rate_float":56401.0395},"CNY":{"code":"CNY","symbol":"&yen;","rate":"440,525.236","description":"Chinese Yuan","rate_float":440525.2361}}}