{"time":{"updated":"Apr 23, 2022 13:34:00 UTC","updatedISO":"2022-04-23T13:34:00+00:00","updateduk":"Apr 23, 2022 at 14:34 BST"},"disclaimer":"This data was produced from the CoinDesk Bitcoin Price Index (USD). Non-USD currency data converted using hourly conversion rate from openexchangerates.org","chartName":"Bitcoin","bpi":{"USD":{"code":"USD","symbol":"&#36;","rate":"39,768.1900","description":"United States Dollar","rate_float":39768.19},"GBP":{"code":"GBP","symbol":"&pound;","rate":"30,973.3355","description":"British Pound Sterling","rate_float":30973.3355},"EUR":{"code":"EUR","symbol":"&euro;","rate":"36,867.8164","description":"Euro","rate_float":36867.8164},"CNY":{"code":"CNY","symbol":"&yen;","rate":"40,202.5000","description":"Chinese Yuan","rate_float":40202.5}}}