{"time":{"updated":"Jan 2, 2025 19:24:17 UTC","updatedISO":"2025-01-02T19:24:17+00:00","updateduk":"Jan 2, 2025 at 19:24 GMT"},"disclaimer":"This data was produced from the CoinDesk Bitcoin Price Index (USD). Non-USD currency data converted using hourly conversion rate from openexchangerates.org","chartName":"Bitcoin","bpi":{"USD":{"code":"USD","symbol":"&#36;","rate":"98,898.091","description":"United States Dollar","rate_float":98898.0908},"GBP":{"code":"GBP","symbol":"&pound;","rate":"78,869.249","description":"British Pound Sterling","rate_float":78869.2494},"EUR":{"code":"EUR","symbol":"&euro;","rate":"94,879.96","description":"Euro","rate_float":94879.9602},"CNY":{"code":"CNY","symbol":"&yen;","rate":"721,817.605","description":"Chinese Yuan","rate_float":721817.6052}}}