{"time":{"updated":"Jan 19, 2025 07:34:07 UTC","updatedISO":"2025-01-19T07:34:07+00:00","updateduk":"Jan 19, 2025 at 07:34 GMT"},"disclaimer":"This data was produced from the CoinDesk Bitcoin Price Index (USD). Non-USD currency data converted using hourly conversion rate from openexchangerates.org","chartName":"Bitcoin","bpi":{"USD":{"code":"USD","symbol":"&#36;","rate":"105,978.052","description":"United States Dollar","rate_float":105978.0522},"GBP":{"code":"GBP","symbol":"&pound;","rate":"84,525.445","description":"British Pound Sterling","rate_float":84525.445},"EUR":{"code":"EUR","symbol":"&euro;","rate":"101,922.696","description":"Euro","rate_float":101922.696},"CNY":{"code":"CNY","symbol":"&yen;","rate":"776,596.569","description":"Chinese Yuan","rate_float":776596.5686}}}