{"time":{"updated":"Jul 16, 2024 18:45:33 UTC","updatedISO":"2024-07-16T18:45:33+00:00","updateduk":"Jul 16, 2024 at 19:45 BST"},"disclaimer":"This data was produced from the CoinDesk Bitcoin Price Index (USD). Non-USD currency data converted using hourly conversion rate from openexchangerates.org","chartName":"Bitcoin","bpi":{"USD":{"code":"USD","symbol":"&#36;","rate":"64,627.185","description":"United States Dollar","rate_float":64627.1846},"GBP":{"code":"GBP","symbol":"&pound;","rate":"49,869.826","description":"British Pound Sterling","rate_float":49869.8255},"EUR":{"code":"EUR","symbol":"&euro;","rate":"59,333.637","description":"Euro","rate_float":59333.6365},"CNY":{"code":"CNY","symbol":"&yen;","rate":"469,303.226","description":"Chinese Yuan","rate_float":469303.2261}}}