{"time":{"updated":"Dec 7, 2024 19:41:56 UTC","updatedISO":"2024-12-07T19:41:56+00:00","updateduk":"Dec 7, 2024 at 19:41 GMT"},"disclaimer":"This data was produced from the CoinDesk Bitcoin Price Index (USD). Non-USD currency data converted using hourly conversion rate from openexchangerates.org","chartName":"Bitcoin","bpi":{"USD":{"code":"USD","symbol":"&#36;","rate":"100,132.068","description":"United States Dollar","rate_float":100132.068},"GBP":{"code":"GBP","symbol":"&pound;","rate":"78,565.723","description":"British Pound Sterling","rate_float":78565.7233},"EUR":{"code":"EUR","symbol":"&euro;","rate":"94,727.84","description":"Euro","rate_float":94727.8402},"CNY":{"code":"CNY","symbol":"&yen;","rate":"727,990.174","description":"Chinese Yuan","rate_float":727990.1741}}}