{"time":{"updated":"Jan 25, 2025 05:49:55 UTC","updatedISO":"2025-01-25T05:49:55+00:00","updateduk":"Jan 25, 2025 at 05:49 GMT"},"disclaimer":"This data was produced from the CoinDesk Bitcoin Price Index (USD). Non-USD currency data converted using hourly conversion rate from openexchangerates.org","chartName":"Bitcoin","bpi":{"USD":{"code":"USD","symbol":"&#36;","rate":"103,773.877","description":"United States Dollar","rate_float":103773.8771},"GBP":{"code":"GBP","symbol":"&pound;","rate":"82,767.45","description":"British Pound Sterling","rate_float":82767.4501},"EUR":{"code":"EUR","symbol":"&euro;","rate":"99,802.866","description":"Euro","rate_float":99802.8659},"CNY":{"code":"CNY","symbol":"&yen;","rate":"760,444.594","description":"Chinese Yuan","rate_float":760444.5942}}}