{"time":{"updated":"Dec 14, 2024 07:39:09 UTC","updatedISO":"2024-12-14T07:39:09+00:00","updateduk":"Dec 14, 2024 at 07:39 GMT"},"disclaimer":"This data was produced from the CoinDesk Bitcoin Price Index (USD). Non-USD currency data converted using hourly conversion rate from openexchangerates.org","chartName":"Bitcoin","bpi":{"USD":{"code":"USD","symbol":"&#36;","rate":"101,927.202","description":"United States Dollar","rate_float":101927.2015},"GBP":{"code":"GBP","symbol":"&pound;","rate":"79,755.283","description":"British Pound Sterling","rate_float":79755.2831},"EUR":{"code":"EUR","symbol":"&euro;","rate":"96,784.974","description":"Euro","rate_float":96784.9742},"CNY":{"code":"CNY","symbol":"&yen;","rate":"738,941.633","description":"Chinese Yuan","rate_float":738941.6326}}}