{"time":{"updated":"Jul 14, 2024 11:52:48 UTC","updatedISO":"2024-07-14T11:52:48+00:00","updateduk":"Jul 14, 2024 at 12:52 BST"},"disclaimer":"This data was produced from the CoinDesk Bitcoin Price Index (USD). Non-USD currency data converted using hourly conversion rate from openexchangerates.org","chartName":"Bitcoin","bpi":{"USD":{"code":"USD","symbol":"&#36;","rate":"60,167.396","description":"United States Dollar","rate_float":60167.396},"GBP":{"code":"GBP","symbol":"&pound;","rate":"47,370.332","description":"British Pound Sterling","rate_float":47370.3324},"EUR":{"code":"EUR","symbol":"&euro;","rate":"55,095.826","description":"Euro","rate_float":55095.826},"CNY":{"code":"CNY","symbol":"&yen;","rate":"436,237.688","description":"Chinese Yuan","rate_float":436237.688}}}