{"time":{"updated":"Mar 28, 2024 13:28:09 UTC","updatedISO":"2024-03-28T13:28:09+00:00","updateduk":"Mar 28, 2024 at 13:28 GMT"},"disclaimer":"This data was produced from the CoinDesk Bitcoin Price Index (USD). Non-USD currency data converted using hourly conversion rate from openexchangerates.org","chartName":"Bitcoin","bpi":{"USD":{"code":"USD","symbol":"&#36;","rate":"70,849.149","description":"United States Dollar","rate_float":70849.1487},"GBP":{"code":"GBP","symbol":"&pound;","rate":"56,045.219","description":"British Pound Sterling","rate_float":56045.2191},"EUR":{"code":"EUR","symbol":"&euro;","rate":"65,547.365","description":"Euro","rate_float":65547.3652},"CNY":{"code":"CNY","symbol":"&yen;","rate":"512,140.156","description":"Chinese Yuan","rate_float":512140.1561}}}