{"time":{"updated":"Oct 12, 2024 08:40:01 UTC","updatedISO":"2024-10-12T08:40:01+00:00","updateduk":"Oct 12, 2024 at 09:40 BST"},"disclaimer":"This data was produced from the CoinDesk Bitcoin Price Index (USD). Non-USD currency data converted using hourly conversion rate from openexchangerates.org","chartName":"Bitcoin","bpi":{"USD":{"code":"USD","symbol":"&#36;","rate":"62,744.856","description":"United States Dollar","rate_float":62744.8557},"GBP":{"code":"GBP","symbol":"&pound;","rate":"48,010.419","description":"British Pound Sterling","rate_float":48010.4185},"EUR":{"code":"EUR","symbol":"&euro;","rate":"57,337.316","description":"Euro","rate_float":57337.3158},"CNY":{"code":"CNY","symbol":"&yen;","rate":"443,367.7","description":"Chinese Yuan","rate_float":443367.6997}}}