{"time":{"updated":"May 8, 2024 08:56:31 UTC","updatedISO":"2024-05-08T08:56:31+00:00","updateduk":"May 8, 2024 at 09:56 BST"},"disclaimer":"This data was produced from the CoinDesk Bitcoin Price Index (USD). Non-USD currency data converted using hourly conversion rate from openexchangerates.org","chartName":"Bitcoin","bpi":{"USD":{"code":"USD","symbol":"&#36;","rate":"62,196.955","description":"United States Dollar","rate_float":62196.9548},"GBP":{"code":"GBP","symbol":"&pound;","rate":"49,867.093","description":"British Pound Sterling","rate_float":49867.0927},"EUR":{"code":"EUR","symbol":"&euro;","rate":"57,919.297","description":"Euro","rate_float":57919.297},"CNY":{"code":"CNY","symbol":"&yen;","rate":"449,435.195","description":"Chinese Yuan","rate_float":449435.1953}}}