{"time":{"updated":"May 8, 2024 15:49:40 UTC","updatedISO":"2024-05-08T15:49:40+00:00","updateduk":"May 8, 2024 at 16:49 BST"},"disclaimer":"This data was produced from the CoinDesk Bitcoin Price Index (USD). Non-USD currency data converted using hourly conversion rate from openexchangerates.org","chartName":"Bitcoin","bpi":{"USD":{"code":"USD","symbol":"&#36;","rate":"62,347.669","description":"United States Dollar","rate_float":62347.6694},"GBP":{"code":"GBP","symbol":"&pound;","rate":"49,905.381","description":"British Pound Sterling","rate_float":49905.3814},"EUR":{"code":"EUR","symbol":"&euro;","rate":"57,997.984","description":"Euro","rate_float":57997.9842},"CNY":{"code":"CNY","symbol":"&yen;","rate":"450,611.546","description":"Chinese Yuan","rate_float":450611.5456}}}