{"time":{"updated":"Jul 18, 2024 14:48:25 UTC","updatedISO":"2024-07-18T14:48:25+00:00","updateduk":"Jul 18, 2024 at 15:48 BST"},"disclaimer":"This data was produced from the CoinDesk Bitcoin Price Index (USD). Non-USD currency data converted using hourly conversion rate from openexchangerates.org","chartName":"Bitcoin","bpi":{"USD":{"code":"USD","symbol":"&#36;","rate":"63,809.137","description":"United States Dollar","rate_float":63809.1366},"GBP":{"code":"GBP","symbol":"&pound;","rate":"49,172.852","description":"British Pound Sterling","rate_float":49172.8521},"EUR":{"code":"EUR","symbol":"&euro;","rate":"58,479.989","description":"Euro","rate_float":58479.989},"CNY":{"code":"CNY","symbol":"&yen;","rate":"463,279.856","description":"Chinese Yuan","rate_float":463279.8557}}}