{"time":{"updated":"Dec 20, 2024 03:45:28 UTC","updatedISO":"2024-12-20T03:45:28+00:00","updateduk":"Dec 20, 2024 at 03:45 GMT"},"disclaimer":"This data was produced from the CoinDesk Bitcoin Price Index (USD). Non-USD currency data converted using hourly conversion rate from openexchangerates.org","chartName":"Bitcoin","bpi":{"USD":{"code":"USD","symbol":"&#36;","rate":"98,550.069","description":"United States Dollar","rate_float":98550.0686},"GBP":{"code":"GBP","symbol":"&pound;","rate":"77,112.768","description":"British Pound Sterling","rate_float":77112.7679},"EUR":{"code":"EUR","symbol":"&euro;","rate":"93,578.218","description":"Euro","rate_float":93578.2177},"CNY":{"code":"CNY","symbol":"&yen;","rate":"714,458.433","description":"Chinese Yuan","rate_float":714458.4326}}}