{"time":{"updated":"Feb 13, 2022 05:53:00 UTC","updatedISO":"2022-02-13T05:53:00+00:00","updateduk":"Feb 13, 2022 at 05:53 GMT"},"disclaimer":"This data was produced from the CoinDesk Bitcoin Price Index (USD). Non-USD currency data converted using hourly conversion rate from openexchangerates.org","chartName":"Bitcoin","bpi":{"USD":{"code":"USD","symbol":"&#36;","rate":"42,288.3570","description":"United States Dollar","rate_float":42288.357},"GBP":{"code":"GBP","symbol":"&pound;","rate":"31,180.3474","description":"British Pound Sterling","rate_float":31180.3474},"EUR":{"code":"EUR","symbol":"&euro;","rate":"37,257.4803","description":"Euro","rate_float":37257.4803},"CNY":{"code":"CNY","symbol":"&yen;","rate":"40,202.5000","description":"Chinese Yuan","rate_float":40202.5}}}