{"time":{"updated":"Apr 15, 2023 06:59:00 UTC","updatedISO":"2023-04-15T06:59:00+00:00","updateduk":"Apr 15, 2023 at 07:59 BST"},"disclaimer":"This data was produced from the CoinDesk Bitcoin Price Index (USD). Non-USD currency data converted using hourly conversion rate from openexchangerates.org","chartName":"Bitcoin","bpi":{"USD":{"code":"USD","symbol":"&#36;","rate":"30,524.6207","description":"United States Dollar","rate_float":30524.6207},"GBP":{"code":"GBP","symbol":"&pound;","rate":"25,506.1288","description":"British Pound Sterling","rate_float":25506.1288},"EUR":{"code":"EUR","symbol":"&euro;","rate":"29,735.4371","description":"Euro","rate_float":29735.4371},"CNY":{"code":"CNY","symbol":"&yen;","rate":"40,202.5000","description":"Chinese Yuan","rate_float":40202.5}}}