{"time":{"updated":"May 5, 2023 20:34:00 UTC","updatedISO":"2023-05-05T20:34:00+00:00","updateduk":"May 5, 2023 at 21:34 BST"},"disclaimer":"This data was produced from the CoinDesk Bitcoin Price Index (USD). Non-USD currency data converted using hourly conversion rate from openexchangerates.org","chartName":"Bitcoin","bpi":{"USD":{"code":"USD","symbol":"&#36;","rate":"29,543.1904","description":"United States Dollar","rate_float":29543.1904},"GBP":{"code":"GBP","symbol":"&pound;","rate":"24,686.0536","description":"British Pound Sterling","rate_float":24686.0536},"EUR":{"code":"EUR","symbol":"&euro;","rate":"28,779.3808","description":"Euro","rate_float":28779.3808},"CNY":{"code":"CNY","symbol":"&yen;","rate":"40,202.5000","description":"Chinese Yuan","rate_float":40202.5}}}