{"time":{"updated":"Nov 30, 2024 12:15:16 UTC","updatedISO":"2024-11-30T12:15:16+00:00","updateduk":"Nov 30, 2024 at 12:15 GMT"},"disclaimer":"This data was produced from the CoinDesk Bitcoin Price Index (USD). Non-USD currency data converted using hourly conversion rate from openexchangerates.org","chartName":"Bitcoin","bpi":{"USD":{"code":"USD","symbol":"&#36;","rate":"96,281.026","description":"United States Dollar","rate_float":96281.0255},"GBP":{"code":"GBP","symbol":"&pound;","rate":"75,600.535","description":"British Pound Sterling","rate_float":75600.5352},"EUR":{"code":"EUR","symbol":"&euro;","rate":"91,020.038","description":"Euro","rate_float":91020.0377},"CNY":{"code":"CNY","symbol":"&yen;","rate":"697,238.302","description":"Chinese Yuan","rate_float":697238.3022}}}