{"time":{"updated":"Nov 3, 2024 10:52:53 UTC","updatedISO":"2024-11-03T10:52:53+00:00","updateduk":"Nov 3, 2024 at 10:52 GMT"},"disclaimer":"This data was produced from the CoinDesk Bitcoin Price Index (USD). Non-USD currency data converted using hourly conversion rate from openexchangerates.org","chartName":"Bitcoin","bpi":{"USD":{"code":"USD","symbol":"&#36;","rate":"68,577.059","description":"United States Dollar","rate_float":68577.0592},"GBP":{"code":"GBP","symbol":"&pound;","rate":"53,045.384","description":"British Pound Sterling","rate_float":53045.384},"EUR":{"code":"EUR","symbol":"&euro;","rate":"63,062.298","description":"Euro","rate_float":63062.2979},"CNY":{"code":"CNY","symbol":"&yen;","rate":"488,446.962","description":"Chinese Yuan","rate_float":488446.9621}}}