{"time":{"updated":"Nov 25, 2024 07:47:40 UTC","updatedISO":"2024-11-25T07:47:40+00:00","updateduk":"Nov 25, 2024 at 07:47 GMT"},"disclaimer":"This data was produced from the CoinDesk Bitcoin Price Index (USD). Non-USD currency data converted using hourly conversion rate from openexchangerates.org","chartName":"Bitcoin","bpi":{"USD":{"code":"USD","symbol":"&#36;","rate":"97,955.703","description":"United States Dollar","rate_float":97955.7033},"GBP":{"code":"GBP","symbol":"&pound;","rate":"77,739.899","description":"British Pound Sterling","rate_float":77739.8991},"EUR":{"code":"EUR","symbol":"&euro;","rate":"93,439.162","description":"Euro","rate_float":93439.1617},"CNY":{"code":"CNY","symbol":"&yen;","rate":"709,591.115","description":"Chinese Yuan","rate_float":709591.1147}}}