{"time":{"updated":"Aug 6, 2024 09:43:52 UTC","updatedISO":"2024-08-06T09:43:52+00:00","updateduk":"Aug 6, 2024 at 10:43 BST"},"disclaimer":"This data was produced from the CoinDesk Bitcoin Price Index (USD). Non-USD currency data converted using hourly conversion rate from openexchangerates.org","chartName":"Bitcoin","bpi":{"USD":{"code":"USD","symbol":"&#36;","rate":"55,379.711","description":"United States Dollar","rate_float":55379.7112},"GBP":{"code":"GBP","symbol":"&pound;","rate":"43,496.554","description":"British Pound Sterling","rate_float":43496.5543},"EUR":{"code":"EUR","symbol":"&euro;","rate":"50,678.971","description":"Euro","rate_float":50678.9705},"CNY":{"code":"CNY","symbol":"&yen;","rate":"395,239.461","description":"Chinese Yuan","rate_float":395239.4608}}}