{"time":{"updated":"May 29, 2024 23:41:03 UTC","updatedISO":"2024-05-29T23:41:03+00:00","updateduk":"May 30, 2024 at 00:41 BST"},"disclaimer":"This data was produced from the CoinDesk Bitcoin Price Index (USD). Non-USD currency data converted using hourly conversion rate from openexchangerates.org","chartName":"Bitcoin","bpi":{"USD":{"code":"USD","symbol":"&#36;","rate":"67,586.375","description":"United States Dollar","rate_float":67586.3749},"GBP":{"code":"GBP","symbol":"&pound;","rate":"53,227.447","description":"British Pound Sterling","rate_float":53227.4468},"EUR":{"code":"EUR","symbol":"&euro;","rate":"62,574.034","description":"Euro","rate_float":62574.0342},"CNY":{"code":"CNY","symbol":"&yen;","rate":"480,728.368","description":"Chinese Yuan","rate_float":480728.3677}}}