{"time":{"updated":"Dec 24, 2024 04:52:55 UTC","updatedISO":"2024-12-24T04:52:55+00:00","updateduk":"Dec 24, 2024 at 04:52 GMT"},"disclaimer":"This data was produced from the CoinDesk Bitcoin Price Index (USD). Non-USD currency data converted using hourly conversion rate from openexchangerates.org","chartName":"Bitcoin","bpi":{"USD":{"code":"USD","symbol":"&#36;","rate":"94,196.674","description":"United States Dollar","rate_float":94196.674},"GBP":{"code":"GBP","symbol":"&pound;","rate":"75,139.839","description":"British Pound Sterling","rate_float":75139.8391},"EUR":{"code":"EUR","symbol":"&euro;","rate":"90,518.671","description":"Euro","rate_float":90518.6707},"CNY":{"code":"CNY","symbol":"&yen;","rate":"687,475.586","description":"Chinese Yuan","rate_float":687475.586}}}