{"time":{"updated":"Dec 23, 2024 07:42:10 UTC","updatedISO":"2024-12-23T07:42:10+00:00","updateduk":"Dec 23, 2024 at 07:42 GMT"},"disclaimer":"This data was produced from the CoinDesk Bitcoin Price Index (USD). Non-USD currency data converted using hourly conversion rate from openexchangerates.org","chartName":"Bitcoin","bpi":{"USD":{"code":"USD","symbol":"&#36;","rate":"95,027.053","description":"United States Dollar","rate_float":95027.053},"GBP":{"code":"GBP","symbol":"&pound;","rate":"75,998.836","description":"British Pound Sterling","rate_float":75998.8359},"EUR":{"code":"EUR","symbol":"&euro;","rate":"91,523.596","description":"Euro","rate_float":91523.5956},"CNY":{"code":"CNY","symbol":"&yen;","rate":"693,621.466","description":"Chinese Yuan","rate_float":693621.4655}}}