{"time":{"updated":"Aug 19, 2024 18:52:58 UTC","updatedISO":"2024-08-19T18:52:58+00:00","updateduk":"Aug 19, 2024 at 19:52 BST"},"disclaimer":"This data was produced from the CoinDesk Bitcoin Price Index (USD). Non-USD currency data converted using hourly conversion rate from openexchangerates.org","chartName":"Bitcoin","bpi":{"USD":{"code":"USD","symbol":"&#36;","rate":"59,049.339","description":"United States Dollar","rate_float":59049.3385},"GBP":{"code":"GBP","symbol":"&pound;","rate":"45,455.649","description":"British Pound Sterling","rate_float":45455.6493},"EUR":{"code":"EUR","symbol":"&euro;","rate":"53,308.385","description":"Euro","rate_float":53308.3846},"CNY":{"code":"CNY","symbol":"&yen;","rate":"421,399.699","description":"Chinese Yuan","rate_float":421399.699}}}