{"time":{"updated":"Aug 27, 2021 11:29:00 UTC","updatedISO":"2021-08-27T11:29:00+00:00","updateduk":"Aug 27, 2021 at 12:29 BST"},"disclaimer":"This data was produced from the CoinDesk Bitcoin Price Index (USD). Non-USD currency data converted using hourly conversion rate from openexchangerates.org","chartName":"Bitcoin","bpi":{"USD":{"code":"USD","symbol":"&#36;","rate":"47,597.9042","description":"United States Dollar","rate_float":47597.9042},"GBP":{"code":"GBP","symbol":"&pound;","rate":"34,727.9545","description":"British Pound Sterling","rate_float":34727.9545},"EUR":{"code":"EUR","symbol":"&euro;","rate":"40,478.6381","description":"Euro","rate_float":40478.6381},"CNY":{"code":"CNY","symbol":"&yen;","rate":"40,202.5000","description":"Chinese Yuan","rate_float":40202.5}}}