{"time":{"updated":"Mar 5, 2024 20:26:49 UTC","updatedISO":"2024-03-05T20:26:49+00:00","updateduk":"Mar 5, 2024 at 20:26 GMT"},"disclaimer":"This data was produced from the CoinDesk Bitcoin Price Index (USD). Non-USD currency data converted using hourly conversion rate from openexchangerates.org","chartName":"Bitcoin","bpi":{"USD":{"code":"USD","symbol":"&#36;","rate":"62,680.969","description":"United States Dollar","rate_float":62680.969},"GBP":{"code":"GBP","symbol":"&pound;","rate":"49,346.721","description":"British Pound Sterling","rate_float":49346.7211},"EUR":{"code":"EUR","symbol":"&euro;","rate":"57,755.31","description":"Euro","rate_float":57755.3104},"CNY":{"code":"CNY","symbol":"&yen;","rate":"451,108.666","description":"Chinese Yuan","rate_float":451108.6657}}}