{"time":{"updated":"Sep 3, 2024 18:47:43 UTC","updatedISO":"2024-09-03T18:47:43+00:00","updateduk":"Sep 3, 2024 at 19:47 BST"},"disclaimer":"This data was produced from the CoinDesk Bitcoin Price Index (USD). Non-USD currency data converted using hourly conversion rate from openexchangerates.org","chartName":"Bitcoin","bpi":{"USD":{"code":"USD","symbol":"&#36;","rate":"58,000.106","description":"United States Dollar","rate_float":58000.1059},"GBP":{"code":"GBP","symbol":"&pound;","rate":"44,304.715","description":"British Pound Sterling","rate_float":44304.7149},"EUR":{"code":"EUR","symbol":"&euro;","rate":"52,594.496","description":"Euro","rate_float":52594.496},"CNY":{"code":"CNY","symbol":"&yen;","rate":"413,041.954","description":"Chinese Yuan","rate_float":413041.9539}}}