{"time":{"updated":"Jan 30, 2025 08:58:41 UTC","updatedISO":"2025-01-30T08:58:41+00:00","updateduk":"Jan 30, 2025 at 08:58 GMT"},"disclaimer":"This data was produced from the CoinDesk Bitcoin Price Index (USD). Non-USD currency data converted using hourly conversion rate from openexchangerates.org","chartName":"Bitcoin","bpi":{"USD":{"code":"USD","symbol":"&#36;","rate":"105,433.667","description":"United States Dollar","rate_float":105433.6673},"GBP":{"code":"GBP","symbol":"&pound;","rate":"84,672.408","description":"British Pound Sterling","rate_float":84672.4076},"EUR":{"code":"EUR","symbol":"&euro;","rate":"100,802.704","description":"Euro","rate_float":100802.7043},"CNY":{"code":"CNY","symbol":"&yen;","rate":"766,154.83","description":"Chinese Yuan","rate_float":766154.83}}}