{"time":{"updated":"Jan 23, 2024 07:37:15 UTC","updatedISO":"2024-01-23T07:37:15+00:00","updateduk":"Jan 23, 2024 at 07:37 GMT"},"disclaimer":"This data was produced from the CoinDesk Bitcoin Price Index (USD). Non-USD currency data converted using hourly conversion rate from openexchangerates.org","chartName":"Bitcoin","bpi":{"USD":{"code":"USD","symbol":"&#36;","rate":"39,858.548","description":"United States Dollar","rate_float":39858.5479},"GBP":{"code":"GBP","symbol":"&pound;","rate":"31,272.499","description":"British Pound Sterling","rate_float":31272.4985},"EUR":{"code":"EUR","symbol":"&euro;","rate":"36,520.674","description":"Euro","rate_float":36520.6735},"CNY":{"code":"CNY","symbol":"&yen;","rate":"282,338.024","description":"Chinese Yuan","rate_float":282338.0241}}}