{"time":{"updated":"Nov 13, 2024 21:12:00 UTC","updatedISO":"2024-11-13T21:12:00+00:00","updateduk":"Nov 13, 2024 at 21:12 GMT"},"disclaimer":"This data was produced from the CoinDesk Bitcoin Price Index (USD). Non-USD currency data converted using hourly conversion rate from openexchangerates.org","chartName":"Bitcoin","bpi":{"USD":{"code":"USD","symbol":"&#36;","rate":"88,817.777","description":"United States Dollar","rate_float":88817.7772},"GBP":{"code":"GBP","symbol":"&pound;","rate":"69,908.117","description":"British Pound Sterling","rate_float":69908.1172},"EUR":{"code":"EUR","symbol":"&euro;","rate":"84,060.697","description":"Euro","rate_float":84060.697},"CNY":{"code":"CNY","symbol":"&yen;","rate":"641,690.677","description":"Chinese Yuan","rate_float":641690.6767}}}