{"time":{"updated":"Dec 5, 2024 15:15:39 UTC","updatedISO":"2024-12-05T15:15:39+00:00","updateduk":"Dec 5, 2024 at 15:15 GMT"},"disclaimer":"This data was produced from the CoinDesk Bitcoin Price Index (USD). Non-USD currency data converted using hourly conversion rate from openexchangerates.org","chartName":"Bitcoin","bpi":{"USD":{"code":"USD","symbol":"&#36;","rate":"103,365.753","description":"United States Dollar","rate_float":103365.7533},"GBP":{"code":"GBP","symbol":"&pound;","rate":"81,060.147","description":"British Pound Sterling","rate_float":81060.1473},"EUR":{"code":"EUR","symbol":"&euro;","rate":"97,819.354","description":"Euro","rate_float":97819.3537},"CNY":{"code":"CNY","symbol":"&yen;","rate":"750,569.745","description":"Chinese Yuan","rate_float":750569.7446}}}