{"time":{"updated":"May 8, 2024 05:20:06 UTC","updatedISO":"2024-05-08T05:20:06+00:00","updateduk":"May 8, 2024 at 06:20 BST"},"disclaimer":"This data was produced from the CoinDesk Bitcoin Price Index (USD). Non-USD currency data converted using hourly conversion rate from openexchangerates.org","chartName":"Bitcoin","bpi":{"USD":{"code":"USD","symbol":"&#36;","rate":"62,613.356","description":"United States Dollar","rate_float":62613.3556},"GBP":{"code":"GBP","symbol":"&pound;","rate":"50,143.468","description":"British Pound Sterling","rate_float":50143.4675},"EUR":{"code":"EUR","symbol":"&euro;","rate":"58,292.721","description":"Euro","rate_float":58292.721},"CNY":{"code":"CNY","symbol":"&yen;","rate":"452,350.188","description":"Chinese Yuan","rate_float":452350.1875}}}