{"time":{"updated":"Apr 6, 2024 04:54:47 UTC","updatedISO":"2024-04-06T04:54:47+00:00","updateduk":"Apr 6, 2024 at 05:54 BST"},"disclaimer":"This data was produced from the CoinDesk Bitcoin Price Index (USD). Non-USD currency data converted using hourly conversion rate from openexchangerates.org","chartName":"Bitcoin","bpi":{"USD":{"code":"USD","symbol":"&#36;","rate":"67,813.096","description":"United States Dollar","rate_float":67813.0956},"GBP":{"code":"GBP","symbol":"&pound;","rate":"53,658.061","description":"British Pound Sterling","rate_float":53658.0613},"EUR":{"code":"EUR","symbol":"&euro;","rate":"62,537.237","description":"Euro","rate_float":62537.2368},"CNY":{"code":"CNY","symbol":"&yen;","rate":"490,478.558","description":"Chinese Yuan","rate_float":490478.5579}}}