{"time":{"updated":"Dec 5, 2024 19:23:13 UTC","updatedISO":"2024-12-05T19:23:13+00:00","updateduk":"Dec 5, 2024 at 19:23 GMT"},"disclaimer":"This data was produced from the CoinDesk Bitcoin Price Index (USD). Non-USD currency data converted using hourly conversion rate from openexchangerates.org","chartName":"Bitcoin","bpi":{"USD":{"code":"USD","symbol":"&#36;","rate":"100,808.742","description":"United States Dollar","rate_float":100808.7421},"GBP":{"code":"GBP","symbol":"&pound;","rate":"79,088.289","description":"British Pound Sterling","rate_float":79088.2889},"EUR":{"code":"EUR","symbol":"&euro;","rate":"95,392.994","description":"Euro","rate_float":95392.994},"CNY":{"code":"CNY","symbol":"&yen;","rate":"731,911.791","description":"Chinese Yuan","rate_float":731911.7909}}}