{"time":{"updated":"Jul 31, 2021 21:42:00 UTC","updatedISO":"2021-07-31T21:42:00+00:00","updateduk":"Jul 31, 2021 at 22:42 BST"},"disclaimer":"This data was produced from the CoinDesk Bitcoin Price Index (USD). Non-USD currency data converted using hourly conversion rate from openexchangerates.org","chartName":"Bitcoin","bpi":{"USD":{"code":"USD","symbol":"&#36;","rate":"41,788.7117","description":"United States Dollar","rate_float":41788.7117},"GBP":{"code":"GBP","symbol":"&pound;","rate":"30,053.0206","description":"British Pound Sterling","rate_float":30053.0206},"EUR":{"code":"EUR","symbol":"&euro;","rate":"35,214.2190","description":"Euro","rate_float":35214.219},"CNY":{"code":"CNY","symbol":"&yen;","rate":"40,202.5000","description":"Chinese Yuan","rate_float":40202.5}}}