{"time":{"updated":"May 10, 2024 06:57:11 UTC","updatedISO":"2024-05-10T06:57:11+00:00","updateduk":"May 10, 2024 at 07:57 BST"},"disclaimer":"This data was produced from the CoinDesk Bitcoin Price Index (USD). Non-USD currency data converted using hourly conversion rate from openexchangerates.org","chartName":"Bitcoin","bpi":{"USD":{"code":"USD","symbol":"&#36;","rate":"63,214.839","description":"United States Dollar","rate_float":63214.8392},"GBP":{"code":"GBP","symbol":"&pound;","rate":"50,494.18","description":"British Pound Sterling","rate_float":50494.1803},"EUR":{"code":"EUR","symbol":"&euro;","rate":"58,664.635","description":"Euro","rate_float":58664.6351},"CNY":{"code":"CNY","symbol":"&yen;","rate":"456,701.927","description":"Chinese Yuan","rate_float":456701.9272}}}